pyflx/__init__.py
pyflx/pyflx.so
pyflx-1.3.0.dist-info/METADATA
pyflx-1.3.0.dist-info/RECORD
pyflx-1.3.0.dist-info/WHEEL
pyflx-1.3.0.dist-info/top_level.txt
