Metadata-Version: 2.1
Name: pyflx
Version: 1.3.0
Summary: Provides Python market data API access to FlexTrade SYM
Home-page: https://github.com/devcartel/pyflx
Author: DevCartel
Author-email: support@devcartel.com
License: MIT
Keywords: flextrade application sym symproxy api market data feed
Platform: UNKNOWN
Classifier: Development Status :: 5 - Production/Stable
Classifier: Intended Audience :: Developers
Classifier: Topic :: Software Development :: Build Tools
Classifier: License :: OSI Approved :: MIT License
Classifier: Programming Language :: Python :: 2
Classifier: Programming Language :: Python :: 2.7
